scripttest.py
scripttest-2.0.post1.dist-info/METADATA
scripttest-2.0.post1.dist-info/WHEEL
scripttest-2.0.post1.dist-info/top_level.txt
scripttest-2.0.post1.dist-info/zip-safe
scripttest-2.0.post1.dist-info/RECORD
